{
  "id": "SEE_SAY_WRITE",
  "title": "See Say Write",
  "sets": [
    {
      "id": "SEE_SAY_WRITE:1-10",
      "title": "Lessons 1-10",
      "terms": [
        "Su:li.",
        "Sǔ:dáli.",
        "Ada.",
        "A:li.",
        "À:su:lo.",
        "Lo:lo.",
        "Salǒ:li.",
        "sa:sa",
        "Sa:sa á:ɂi.",
        "Sali.",
        "Ǐ:náda.",
        "Sa:sa aná:ɂi.",
        "Iná:ɂi.",
        "á:su:líɂa.",
        "I:sa à:gíɂa sa:sa",
        "À:hli:ló:ɂa.",
        "Gi:hli aná:ɂi."
      ]
    },
    {
      "id": "SEE_SAY_WRITE:11-20",
      "title": "Lessons 11-20",
      "terms": [
        "Salǒ:li dù:du:lí na gi:hli.",
        "Sali dù:nadu:lí na sa:sa.",
        "sa:ɂdu",
        "Sa:ɂdu à:tlíɂili.",
        "Gǎ:da.",
        "Gǐ:ga.",
        "Ga̋:du",
        "Gà:du:li̋:da á:su:líɂa.",
        "Ga:sgilo.",
        "Anà:ga:lǐ:sgi.",
        "À:sgâ:ga.",
        "Sdù:di.",
        "Di:da:sdù:di̋.",
        "Sǔ:dáli diga:sgilo dù:nadu:lí.",
        "Gi:hli à:giganǎ:díɂa.",
        "U:nv̌:di ù:du:lí na u:sdi̋.",
        "Dina:da:hli:lò:sdi̋:sgi ù:nv:nv́:ga.",
        "Si:nv̋:da.",
        "Ga̋:du agigísi na gi:hli.",
        "Agá:li:siga.",
        "Ó:si.",
        "Usdi̋ ó:si.",
        "O:gana anahli gi:hli.",
        "Yǒ:na á:ɂi.",
        "À:giyó:si.",
        "Diga:da:yo:sdi.",
        "Ò:gina:li̋ ù:yó:siha.",
        "Hadǐ:da!",
        "O:síyo hada."
      ]
    },
    {
      "id": "SEE_SAY_WRITE:21-30",
      "title": "Lessons 21-30",
      "terms": [
        "Áɂni.",
        "Sasa ù:niga:sga.",
        "U:ne̋:ga gi:hli.",
        "Dida:náɂnv̋ iné:na.",
        "Ga̋:du u:nigana̋:sda duwá:duha.",
        "U:nv̌:di ù:hwasga.",
        "Ajaɂdi.",
        "Jayó:sihas?",
        "Jalí:si.",
        "Jayó:li.",
        "I:ya.",
        "Salǒ:li gaɂnǐ:ya na gi:hli.",
        "Tǔ:ya dù:du:lí.",
        "Ji:sdu.",
        "U:ni:ji:ya dù:hyoha na asgaya.",
        "Ha:wiya.",
        "Wiɂsi.",
        "Jí:sgwa.",
        "Sihgwa.",
        "Sihgwa ha:wiya à:gwadu:lí.",
        "Ji:sgwada.",
        "wě:sa.",
        "Wě:sa nigawe.",
        "Sa:sa na:niwe.",
        "Ayv:wi:ya̋.",
        "Ayv.",
        "Ahyv:dagwalò:sgi."
      ]
    },
    {
      "id": "SEE_SAY_WRITE:31-40",
      "title": "Lessons 31-40",
      "terms": [
        "Na agayv̌:líge̋ ù:yó:si, ge:líɂa.",
        "Ada:kéhdi ù:du:lí na agě:hya.",
        "Ajaɂdi ga:tíga na asgaya.",
        "Tiyǒ:háɂli gaɂnǐ:ya na ǐ:náda.",
        "O:sǐ:yu iyunalsdà:hnéhdi.",
        "Ő:sda a:gì:sdi uyu:ti.",
        "Dlo:ge̋:si winè:da tǔ:ya gà:yő:hli widinadági.",
        "Ani:yv:wi:ya̋ dà:nadlo:sga.",
        "Niga̋:da ani:yv:wi:ya̋ ù:natloyâ:sdiha.",
        "Ama sgidlì:sdasi.",
        "Ǔ:gáma à:gwadu:lí.",
        "Kilő anisgaya danidô:ga.",
        "Ǐ:náda gahnǐ:dô na asgaya.",
        "Gadogi u:sdi?",
        "Di:là:sǔ:lo dù:wà:dù:la:chisi na à:lâ:sgalǐ:sgi.",
        "Idalà:sgala.",
        "Jǒ:lani",
        "Jǒ:lani ù:kiɂla wě:sa.",
        "Joɂi iyáni wě:sa ani̋:da à:ni:hlína.",
        "Jǒ:lani tisduɂi.",
        "Da:hnawa à:sgwaliha.",
        "Ayő:hli ù:hnawâ:sdiha.",
        "Uwě:hnaɂi ganě:la na jididá:ne:la.",
        "Awǒ:háɂli u:gì:dáhli gà:nǐ:dô na ayv:wi:ya̋.",
        "Jalagi gawó:ni na ayó:ne:ga.",
        "Nv:wô:ti ù:du:lí na udanili."
      ]
    },
    {
      "id": "SEE_SAY_WRITE:41-50",
      "title": "Lessons 41-50",
      "terms": [
        "Kanu:na nigaweɂa.",
        "U:sdi̋ kanawô:ga.",
        "Kǎ:hwi widayù:hwasi dì:da:náɂnv̋:i.",
        "Di:sésdi dù:wo:hwě:lâ.",
        "Kalsě:ji ù:du:lí na ayő:hli.",
        "Sě:di dà:gíɂa na salǒ:li.",
        "Sgiga:ɂdu ù:dalula nvhgi.",
        "Digadv́:di.",
        "Gadò hà:dv́:ne?",
        "Digadv́:di à:yo:sda na ù:da:ge̋:da achű:ja.",
        "A:dlawáɂdv̋",
        "U:hyv:dla ama à:gwadu:lí.",
        "Áhani ù:dlanv:da.",
        "Hisgi",
        "Hi:yo:lì:gis na asgaya?",
        "Ganv:hi̋:da ù:stihga na age:hyű:ja.",
        "Hisgi aye̋:hli à:hlíɂili.",
        "I:ga e̋:hi nv:da kala.",
        "Hiɂa e:do:da.",
        "Áhani jǒ:hlê:sdi.",
        "Di:da:náɂnv̋ widage:doli hle̋:ga.",
        "U:do:hiyű ù:di:hléhga."
      ]
    },
    {
      "id": "SEE_SAY_WRITE:51-60",
      "title": "Lessons 51-60",
      "terms": [
        "Ganv:gwalő:sdi e:sgv́hsi.",
        "Wě:sa nigawè:sgv́ gà:tv:gí:ɂa.",
        "Gadō u:sdi à:gowhtí na gi:tli.",
        "Digo:hwě:lò:di è:sgidisi.",
        "Ji:sdu ate:sda na gi:tli.",
        "Dihnawo dà:tě:sga.",
        "Ǔ:tana yǒ:na ji:gò:wahtā.",
        "Gv:he anahliha gi:hli.",
        "Wǎ:húhi nigawè:sgv́ gà:tv:gíɂa.",
        "Ni! Go:hű:sdi nigaweɂa.",
        "Hila̋ Ijade:tiyv̋:da",
        "Sohi aninv:hi̋:da dinute:suga.",
        "Sóhně:la aye̋:hli à:tlíɂili",
        "À:sǒ:hyv̋ ù:kila jitǎ:ga.",
        "Hila̋ ǐ:ga̋ juwě:ji dejadu:lí?",
        "Hila̋ iyú:de:tiyv̋:da hiɂa achű:ja.",
        "Ju:ni:là:wisdi̋ idè:na.",
        "Gwiligi dù:do:ɂa achű:ja."
      ]
    },
    {
      "id": "SEE_SAY_WRITE:61-70",
      "title": "Lessons 61-70",
      "terms": [
        "Gano:hali:dő:hi gano:halǐ:dô:ha.",
        "Gá:gō sdà:hlino:héha.",
        "Jí:sdv:na du:gwe:nù:gi na achű:ja.",
        "Gè:hv́ ǐ:gó:hi̋:da gina:li̋ gè:sé:sdi.",
        "Dù:do:ɂa go:hwě:lí:ɂa.",
        "Dejadó:ɂa hohwě:lâ:nvɂi.",
        "Howa hada.",
        "Ahő:li ù:wanhga sgwà:hle̋:sdi.",
        "Hale:hwisda.",
        "Ǐ:jú:la jalagi ale yó:ne:ga degawó:ni.",
        "Gaɂle̋:ni ù:we:hisdâ:neha na ayő:hli.",
        "Hila̋ɂiyv à:dale:nǐ:sgó gő:la.",
        "Ijéɂiyű:sdi ulsǔ:hwi:da ù:hnû:wa.",
        "Ama à:jě:wíɂa na achű:ja.",
        "Di:je̋ dilà:sǔ:lo dù:du:lí.",
        "Akǔ:gi̋:sdi è:sgidisi.",
        "U:gù:ku nigawè:sgv́ gà:tv:gí:ɂa.",
        "Hila̋ɂiyv gvnsgó kuwa:ya.",
        "U:sgwo:hli̋ ù:we:hisdâ:ne na ayő:hli.",
        "Dijalagi digwo:hwě:lô:di gadè:lohgwáɂa.",
        "U:dlv̋:gi",
        "Na u:sdi̋ gahlv:sga.",
        "Sv:do:ni kali̋ kanù:gahli gadagi.",
        "Sv̀:gi ǐ:náge̋ e̋:hi giniyalú:ga.",
        "Ha:dlv wijě:dô:lě sv:hi?"
      ]
    },
    {
      "id": "SEE_SAY_WRITE:71-84",
      "title": "Lessons 71-84",
      "terms": [
        "Igv:yi̋, taɂli:ne̋, joɂi:ne̋, nvhgi:ne̋,",
        "Wǎ:ji dà:sdá:yidiɂa.",
        "Wo:yi nigawè:sgv́ gà:tv:gí:ɂa.",
        "Gaɂlo:hni kaɂlv̋ anvnsgó unitelvládi.",
        "Íhě:dô:lv:ɂi.",
        "Ajvgalí:yé:di ga:nǐ:dô:ha.",
        "De:jv̋ysdv dekdlǒ:hi.",
        "Hi:yo:lì:gis kilő dludlu jù:do:ɂǐ:da?",
        "Ada ti:sdlû:hya.",
        "Ha:dlv dajì:hluni hiɂa gǎ:da?",
        "E:li̋:gwu.",
        "Sǐ:gwu jinihiwi.",
        "Sà:gwű aye̋:hli à:tlíɂili.",
        "Hla go:hű:sdi yigà:tv:gí:ɂa.",
        "Hlawò:tu:hi̋ nigalsdi:sgó yù:ga:hnana.",
        "Hla yà:gwanhta.",
        "Nű:la! À:gwv:nv́:ga.",
        "Agwa̋:sa wigě:dô:li dida:náɂnv̋ɂi.",
        "À:gwv̌:ké:wa dejadó:ɂv̌:ɂi.",
        "Hihv̌:na.",
        "Dijalagi digigo:lǐ:yê:di disgwé:hyo:hv̀:ga.",
        "Idalsdà:yv:hv̀:ga.",
        "Tale:hv̀:ga.",
        "Wǔ:tanv̋ gahljǒ:de ù:su:yé:sv̌.",
        "Wǔ:dé:lì:gv̋ idí:dla wǔ:dé:lì:gi nv:da.",
        "Jǔ:gá:nawv̋.",
        "Jǔ:gá:nawv̋ wanikti sasa.",
        "E:li̋:gwus dida:náɂnv̋ yiwvhé:da?",
        "U:dlv̋:gi kanv:wv̀:ga na gáɂnakti.",
        "Me:li.",
        "Amé:gwő de:gá:sóhgi áyosgi.",
        "Jimi dù:do:ɂa hiɂa achű:ja.",
        "Kě:míli ù:kilv̀:di ji:gò:wahta.",
        "Maga sóhně:line̋ à:yâ:tohlv̋ ajino:héha Mosi.",
        "Jedô:lvhis mu:di?"
      ]
    }
  ]
}
